__init__.py
scheduler.py
speedscheduler.py
speedtester.py
tester.py
speed_tester-0.1.14.dist-info/DESCRIPTION.rst
speed_tester-0.1.14.dist-info/METADATA
speed_tester-0.1.14.dist-info/RECORD
speed_tester-0.1.14.dist-info/WHEEL
speed_tester-0.1.14.dist-info/entry_points.txt
speed_tester-0.1.14.dist-info/metadata.json
speed_tester-0.1.14.dist-info/top_level.txt
