Metadata-Version: 2.0
Name: speed-tester
Version: 0.1.14
Summary: Test the speed of your network connection and send the result to a monitor.
Home-page: https://github.com/jw/speed-tester
Author: Jan Willems
Author-email: jw@elevenbits.com
License: MIT
Platform: UNKNOWN
Classifier: Development Status :: 4 - Beta
Classifier: Environment :: Console
Classifier: Intended Audience :: System Administrators
Classifier: Natural Language :: Dutch
Classifier: Natural Language :: English
Classifier: License :: OSI Approved :: MIT License
Classifier: Operating System :: POSIX :: Linux
Classifier: Programming Language :: Python
Classifier: Programming Language :: Python :: Implementation :: CPython
Classifier: Topic :: System :: Networking
Requires-Python: ~=3.6
Requires-Dist: requests
Requires-Dist: python-crontab
Requires-Dist: speedtest-cli
